foo_alpha/__init__.py
foo_alpha-2.0.dist-info/LICENSE.txt
foo_alpha-2.0.dist-info/METADATA
foo_alpha-2.0.dist-info/WHEEL
foo_alpha-2.0.dist-info/top_level.txt
foo_alpha-2.0.dist-info/RECORD
