Metadata-Version: 2.1
Name: foo_alpha
Version: 2.0
Summary: A useful module
Home-page: UNKNOWN
Author: Man foo_alpha
Author-email: foomail@foo.com
License: UNKNOWN
Platform: UNKNOWN
License-File: LICENSE.txt
